DiscordTickets/__init__.py
DiscordTickets/ticket.py
DiscordTickets-0.0.1.dist-info/METADATA
DiscordTickets-0.0.1.dist-info/WHEEL
DiscordTickets-0.0.1.dist-info/top_level.txt
DiscordTickets-0.0.1.dist-info/RECORD
