Metadata-Version: 2.1
Name: DiscordTickets
Version: 0.0.1
Summary: A simple Discord Ticket bot package
Home-page: UNKNOWN
Author: Ian Cheung
Author-email: support@ianbrawlstars.com
License: UNKNOWN
Keywords: python,first package
Platform: UNKNOWN
Classifier: Development Status :: 3 - Alpha
Classifier: Intended Audience :: Education
Classifier: Programming Language :: Python :: 2
Classifier: Programming Language :: Python :: 3
Classifier: Operating System :: MacOS :: MacOS X
Classifier: Operating System :: Microsoft :: Windows
